LICENSE.md
README.md
setup.py
bin/lightctl
lightctl/__init__.py
lightctl/config.py
lightctl/lightup_client.py
lightctl/util.py
lightctl/version.py
lightctl.egg-info/PKG-INFO
lightctl.egg-info/SOURCES.txt
lightctl.egg-info/dependency_links.txt
lightctl.egg-info/requires.txt
lightctl.egg-info/top_level.txt
lightctl/client/__init__.py
lightctl/client/base_client.py
lightctl/client/datapoint_client.py
lightctl/client/healthz_client.py
lightctl/client/incident_client.py
lightctl/client/metric_client.py
lightctl/client/monitor_client.py
lightctl/client/profiler_client.py
lightctl/client/source_client.py
lightctl/client/user_client.py
lightctl/client/workspace_client.py
lightctl/command/__init__.py
lightctl/command/common.py
lightctl/command/metric_command.py
lightctl/command/monitor_command.py
lightctl/command/source_command.py
lightctl/command/version_command.py
lightctl/command/workspace_command.py